pyweathercli/__init__.py
pyweathercli/cli.py
pyweathercli/config.json
pyweathercli-0.0.4.dist-info/LICENSE
pyweathercli-0.0.4.dist-info/METADATA
pyweathercli-0.0.4.dist-info/WHEEL
pyweathercli-0.0.4.dist-info/entry_points.txt
pyweathercli-0.0.4.dist-info/top_level.txt
pyweathercli-0.0.4.dist-info/RECORD
