Metadata-Version: 2.1
Name: pyweathercli
Version: 0.0.4
Summary: A cli using click for weather
Home-page: https://github.com/A-Trash-Coder/pyweathercli
Author: Gavyn Stanley
License: UNKNOWN
Platform: UNKNOWN
Requires-Dist: click
Requires-Dist: pyfiglet
Requires-Dist: pyowm
Requires-Dist: colorama
